{
    "corpus": "unannotated text corpus of any format",
    "parallel-corpus": "aligned translations of text of two languages or more",
    "morphology-tagged-corpus": "PoS tagged, lemmatized, morphologically disambiguated text",
    "treebank": "turkish wordnet etc..",
    "dictionary": "dictionary",
    "lexicon": "lexicon, a set of vocabulary",
    "word-vectors": "set of pretrained word vectors",
    "language-model": "pretrained weights of language model",
    "morphology-model": "software or model for morphological anaylsis",
    "parser": "software or model for dependency parsing",
    "machine-translation-model": "software or model",
    "nlp-toolkit": "toolkit for turkish/generic nlp",
    "ner-tagger": "named entity recognition tagging software or model",
    "rdf-triples": "rdf triples, knowledge graphs and information retrieval"
}